ellishape_cli/__init__.py
ellishape_cli/__main__.py
ellishape_cli/cli.py
ellishape_cli/get_kind_list.py
ellishape_cli/global_vars.py
ellishape_cli/plot_matrix.py
ellishape_cli/split.py
ellishape_cli/tree.py
ellishape_cli/show/biophylo-3.py
ellishape_cli/show/tree2pic.py
ellishape_cli-1.23.0.dist-info/METADATA
ellishape_cli-1.23.0.dist-info/WHEEL
ellishape_cli-1.23.0.dist-info/RECORD
