Metadata-Version: 2.4
Name: ellishape-cli
Version: 1.23.0
Summary: Command-line version of ellishape
Project-URL: Homepage, https://www.plantplus.cn/ElliShape/
Author-email: Ping Wu <wpwupingwp@outlook.com>, Sally yang <2500876951@qq.com>
License: MIT
Classifier: License :: OSI Approved :: MIT License
Classifier: Operating System :: OS Independent
Classifier: Programming Language :: Python :: 3
Requires-Python: >=3.11
Requires-Dist: biopython>=1.85
Requires-Dist: loguru>=0.7.2
Requires-Dist: matplotlib>=3.10.7
Requires-Dist: numpy>1.26
Requires-Dist: opencv-contrib-python>=4.10.0.84
Requires-Dist: scikit-bio>=0.6.3
Requires-Dist: scipy>=1.16.2
